[
	{
		"id": 1,
		"author": "Александр П.",
		"rating": 5,
		"car": "BMW X5 xDrive40i",
		"text": "Великолепный автомобиль! Владею уже год, никаких нареканий. Комфорт на высшем уровне, динамика впечатляет. Рекомендую всем!",
		"date": "2024-01-15"
	},
	{
		"id": 2,
		"author": "Мария К.",
		"rating": 5,
		"car": "BMW 5 серии",
		"text": "Моя мечта сбылась! Отличный сервис при покупке, менеджеры всё объяснили и помогли с выбором комплектации.",
		"date": "2024-01-12"
	},
	{
		"id": 3,
		"author": "Дмитрий С.",
		"rating": 4,
		"car": "BMW 3 серии",
		"text": "Хороший автомобиль для своего класса. Немного жесткая подвеска на неровностях, но управляемость отличная.",
		"date": "2024-01-10"
	},
	{
		"id": 4,
		"author": "Елена В.",
		"rating": 5,
		"car": "BMW iX",
		"text": "Перешла с бензинового авто на электрику и не жалею! Запас хода впечатляет, интерьер просто космос.",
		"date": "2024-01-08"
	},
	{
		"id": 5,
		"author": "Сергей М.",
		"rating": 5,
		"car": "BMW X3",
		"text": "Отличный семейный автомобиль. Просторный, комфортный, экономичный. Дети в восторге от панорамной крыши!",
		"date": "2024-01-05"
	},
	{
		"id": 6,
		"author": "Андрей Н.",
		"rating": 4,
		"car": "BMW M3",
		"text": "Настоящий спорткар на каждый день. Управляемость потрясающая, звук двигателя заставляет улыбаться.",
		"date": "2024-01-03"
	},
	{
		"id": 7,
		"author": "Ольга Р.",
		"rating": 5,
		"car": "BMW 7 серии",
		"text": "Роскошь и технологии на высшем уровне. Кинотеатр Theatre Screen - это что-то невероятное!",
		"date": "2023-12-28"
	},
	{
		"id": 8,
		"author": "Игорь Л.",
		"rating": 3,
		"car": "BMW X1",
		"text": "Неплохой компактный кроссовер, но за эти деньги хотелось бы больше оснащения в базе.",
		"date": "2023-12-25"
	},
	{
		"id": 9,
		"author": "Наталья Ф.",
		"rating": 5,
		"car": "BMW i4",
		"text": "Идеальный электрокар! Тихий, быстрый, красивый. Зарядка не проблема благодаря хорошей инфраструктуре.",
		"date": "2023-12-22"
	},
	{
		"id": 10,
		"author": "Павел Д.",
		"rating": 4,
		"car": "BMW X7",
		"text": "Огромный и комфортный. Третий ряд сидений реально рабочий. Расход топлива, конечно, немаленький.",
		"date": "2023-12-20"
	},
	{
		"id": 11,
		"author": "Виктория А.",
		"rating": 5,
		"car": "BMW 4 серии",
		"text": "Купе моей мечты! Дизайн спорный, но мне очень нравится. Привлекает внимание на дороге.",
		"date": "2023-12-18"
	},
	{
		"id": 12,
		"author": "Константин Б.",
		"rating": 5,
		"car": "BMW M5",
		"text": "Уникальное сочетание мощи и комфорта. 625 л.с. под капотом - это нечто невообразимое!",
		"date": "2023-12-15"
	},
	{
		"id": 13,
		"author": "Анна Г.",
		"rating": 4,
		"car": "BMW 2 серии",
		"text": "Компактный, маневренный, стильный. Идеален для города. Парковка - одно удовольствие.",
		"date": "2023-12-12"
	},
	{
		"id": 14,
		"author": "Михаил Е.",
		"rating": 5,
		"car": "BMW Z4",
		"text": "Родстер для души! Открытый верх, задний привод, отличная управляемость. Что ещё нужно для счастья?",
		"date": "2023-12-10"
	},
	{
		"id": 15,
		"author": "Татьяна Ж.",
		"rating": 4,
		"car": "BMW X6",
		"text": "Красивый и мощный. Единственный минус - обзорность назад из-за наклонной крыши.",
		"date": "2023-12-08"
	},
	{
		"id": 16,
		"author": "Роман З.",
		"rating": 5,
		"car": "BMW 8 серии",
		"text": "Гранд-турер в лучшем смысле этого слова. Комфорт на дальних расстояниях невероятный.",
		"date": "2023-12-05"
	},
	{
		"id": 17,
		"author": "Светлана И.",
		"rating": 5,
		"car": "BMW i7",
		"text": "Будущее уже здесь! Электрический флагман с театральным экраном - это надо видеть!",
		"date": "2023-12-03"
	},
	{
		"id": 18,
		"author": "Алексей К.",
		"rating": 4,
		"car": "BMW M2",
		"text": "Компактная злая машинка! На треке показывает себя великолепно. Для города немного жестковата.",
		"date": "2023-12-01"
	},
	{
		"id": 19,
		"author": "Юлия Л.",
		"rating": 5,
		"car": "BMW 330e",
		"text": "Гибрид - отличный компромисс. В городе езжу на электричестве, на трассе - на бензине.",
		"date": "2023-11-28"
	},
	{
		"id": 20,
		"author": "Владимир М.",
		"rating": 5,
		"car": "BMW X5 M",
		"text": "Семейный спорткар! Жена довольна комфортом, я - мощностью. Дети любят быстрое ускорение.",
		"date": "2023-11-25"
	},
	{
		"id": 21,
		"author": "Екатерина Н.",
		"rating": 4,
		"car": "BMW iX3",
		"text": "Отличный электрический кроссовер. Запас хода хватает на неделю городских поездок.",
		"date": "2023-11-22"
	},
	{
		"id": 22,
		"author": "Денис О.",
		"rating": 5,
		"car": "BMW M4",
		"text": "Легенда! Каждая поездка - это удовольствие. Звук выхлопа заставляет оборачиваться прохожих.",
		"date": "2023-11-20"
	},
	{
		"id": 23,
		"author": "Ирина П.",
		"rating": 4,
		"car": "BMW X2",
		"text": "Стильный городской кроссовер. Небольшой, но вместительный. Парковочные датчики очень помогают.",
		"date": "2023-11-18"
	},
	{
		"id": 24,
		"author": "Артём Р.",
		"rating": 5,
		"car": "BMW 530d",
		"text": "Дизель на современном BMW - это не про тракторный звук. Тихо, экономично, мощно!",
		"date": "2023-11-15"
	},
	{
		"id": 25,
		"author": "Марина С.",
		"rating": 5,
		"car": "BMW X3 M",
		"text": "Компактный, но очень мощный! 510 л.с. в таком кузове - это нечто!",
		"date": "2023-11-12"
	},
	{
		"id": 26,
		"author": "Николай Т.",
		"rating": 4,
		"car": "BMW 3 серии Touring",
		"text": "Практичный универсал с отличной управляемостью. Багажник огромный!",
		"date": "2023-11-10"
	},
	{
		"id": 27,
		"author": "Галина У.",
		"rating": 5,
		"car": "BMW 740d",
		"text": "Дизельный флагман - это экономия на топливе без потери комфорта и мощности.",
		"date": "2023-11-08"
	},
	{
		"id": 28,
		"author": "Олег Ф.",
		"rating": 4,
		"car": "BMW X4",
		"text": "Красивый кроссовер-купе. Немного тесновато сзади из-за крыши, но выглядит отлично.",
		"date": "2023-11-05"
	},
	{
		"id": 29,
		"author": "Людмила Х.",
		"rating": 5,
		"car": "BMW iX1",
		"text": "Компактный электрокар идеален для города. Зарядки хватает на несколько дней.",
		"date": "2023-11-03"
	},
	{
		"id": 30,
		"author": "Григорий Ц.",
		"rating": 5,
		"car": "BMW 5 серии Touring",
		"text": "Бизнес-универсал на все случаи жизни. Командировки и семейные путешествия - легко!",
		"date": "2023-11-01"
	},
	{
		"id": 31,
		"author": "Жанна Ч.",
		"rating": 4,
		"car": "BMW 4 серии Кабриолет",
		"text": "Мечта любой девушки! Открытый верх и стильный дизайн. Зимой, правда, мало используется.",
		"date": "2023-10-28"
	},
	{
		"id": 32,
		"author": "Борис Ш.",
		"rating": 5,
		"car": "BMW M8",
		"text": "Невероятная машина! 625 л.с. и роскошный интерьер - идеальное сочетание.",
		"date": "2023-10-25"
	},
	{
		"id": 33,
		"author": "Вера Щ.",
		"rating": 4,
		"car": "BMW X1 xDrive25e",
		"text": "Гибридный X1 - отличный выбор для тех, кто хочет экономить и не терять в мощности.",
		"date": "2023-10-22"
	},
	{
		"id": 34,
		"author": "Кирилл Э.",
		"rating": 5,
		"car": "BMW 2 серии Active Tourer",
		"text": "Компактвэн от BMW - отличный семейный автомобиль. Удобно садить детей в кресла.",
		"date": "2023-10-20"
	},
	{
		"id": 35,
		"author": "Зоя Ю.",
		"rating": 5,
		"car": "BMW X5 xDrive45e",
		"text": "Гибридный X5 - лучшее из двух миров. По городу на электричестве, за город - на бензине.",
		"date": "2023-10-18"
	},
	{
		"id": 36,
		"author": "Фёдор Я.",
		"rating": 4,
		"car": "BMW 220i Gran Coupé",
		"text": "Стильный четырёхдверный coupé для молодых. Немного тесновато сзади, но красиво.",
		"date": "2023-10-15"
	},
	{
		"id": 37,
		"author": "Антон В.",
		"rating": 5,
		"car": "BMW X5",
		"text": "Второй X5 в семье. Первый отездил 5 лет без проблем. Новый ещё лучше!",
		"date": "2023-10-12"
	},
	{
		"id": 38,
		"author": "Полина Г.",
		"rating": 5,
		"car": "BMW 3 серии",
		"text": "Классика BMW! Управляемость на высоте, дизайн вне времени.",
		"date": "2023-10-10"
	},
	{
		"id": 39,
		"author": "Максим Д.",
		"rating": 4,
		"car": "BMW X3 xDrive30i",
		"text": "Отличный средний кроссовер. Подходит для города и загородных поездок.",
		"date": "2023-10-08"
	},
	{
		"id": 40,
		"author": "Дарья Е.",
		"rating": 5,
		"car": "BMW iX",
		"text": "Электрический флагман! Технологии будущего уже сегодня. Особенно нравится салон.",
		"date": "2023-10-05"
	},
	{
		"id": 41,
		"author": "Станислав Ж.",
		"rating": 4,
		"car": "BMW 5 серии",
		"text": "Надёжный бизнес-седан. Комфорт в пробках, динамика на трассе.",
		"date": "2023-10-03"
	},
	{
		"id": 42,
		"author": "Алина З.",
		"rating": 5,
		"car": "BMW X7",
		"text": "Большой семейный автомобиль. Места хватит всем! Качество материалов на высоте.",
		"date": "2023-10-01"
	},
	{
		"id": 43,
		"author": "Евгений И.",
		"rating": 5,
		"car": "BMW M3",
		"text": "Мечта с детства! Наконец-то смог себе позволить. Каждый день как праздник за рулём.",
		"date": "2023-09-28"
	},
	{
		"id": 44,
		"author": "Надежда К.",
		"rating": 4,
		"car": "BMW X1",
		"text": "Компактный и экономичный. Для города - идеально. За городом немного не хватает мощности.",
		"date": "2023-09-25"
	},
	{
		"id": 45,
		"author": "Тимур Л.",
		"rating": 5,
		"car": "BMW 7 серии",
		"text": "Лучший автомобиль, которым я когда-либо владел. Роскошь во всём!",
		"date": "2023-09-22"
	},
	{
		"id": 46,
		"author": "Регина М.",
		"rating": 5,
		"car": "BMW 4 серии",
		"text": "Красивое купе! Дизайн решётки уже полюбился. Привлекает много внимания.",
		"date": "2023-09-20"
	},
	{
		"id": 47,
		"author": "Валерий Н.",
		"rating": 4,
		"car": "BMW 330d",
		"text": "Дизельная трёшка - экономичная и динамичная. Идеально для дальних поездок.",
		"date": "2023-09-18"
	},
	{
		"id": 48,
		"author": "Кристина О.",
		"rating": 5,
		"car": "BMW i4",
		"text": "Электрическое Gran Coupé - это любовь с первого взгляда! И с первой поездки!",
		"date": "2023-09-15"
	},
	{
		"id": 49,
		"author": "Арсений П.",
		"rating": 5,
		"car": "BMW X6",
		"text": "Спортивный SAC - уникальный автомобиль. Ни на что не похож!",
		"date": "2023-09-12"
	},
	{
		"id": 50,
		"author": "Лариса Р.",
		"rating": 4,
		"car": "BMW 2 серии",
		"text": "Маленький, но удаленький! Отличная машина для девушки.",
		"date": "2023-09-10"
	},
	{
		"id": 51,
		"author": "Василий С.",
		"rating": 5,
		"car": "BMW X5 M",
		"text": "Мощь и комфорт в одном флаконе. 625 л.с. - это невероятно!",
		"date": "2023-09-08"
	},
	{
		"id": 52,
		"author": "Оксана Т.",
		"rating": 5,
		"car": "BMW 530e",
		"text": "Гибридная пятёрка - идеальный компромисс между экологичностью и мощностью.",
		"date": "2023-09-05"
	},
	{
		"id": 53,
		"author": "Леонид У.",
		"rating": 4,
		"car": "BMW Z4",
		"text": "Отличный родстер для лета! Зимой, правда, стоит в гараже.",
		"date": "2023-09-03"
	},
	{
		"id": 54,
		"author": "Софья Ф.",
		"rating": 5,
		"car": "BMW X3",
		"text": "Второй X3 в семье. Первый продали с большим сожалением, сразу купили новый.",
		"date": "2023-09-01"
	},
	{
		"id": 55,
		"author": "Пётр Х.",
		"rating": 5,
		"car": "BMW 8 серии",
		"text": "Gran Turismo в лучших традициях. Дальние поездки - одно удовольствие!",
		"date": "2023-08-28"
	},
	{
		"id": 56,
		"author": "Яна Ц.",
		"rating": 4,
		"car": "BMW iX3",
		"text": "Электрический X3 - очень практичный выбор. Зарядки хватает надолго.",
		"date": "2023-08-25"
	},
	{
		"id": 57,
		"author": "Глеб Ч.",
		"rating": 5,
		"car": "BMW M2",
		"text": "Маленький монстр! На треке показывает невероятные результаты.",
		"date": "2023-08-22"
	},
	{
		"id": 58,
		"author": "Варвара Ш.",
		"rating": 5,
		"car": "BMW 3 серии Touring",
		"text": "Спортивный универсал для активной семьи. Велосипеды, лыжи - всё помещается!",
		"date": "2023-08-20"
	},
	{
		"id": 59,
		"author": "Эдуард Щ.",
		"rating": 4,
		"car": "BMW 740d",
		"text": "Дизельный флагман - редкость на дорогах. Экономичен при этом.",
		"date": "2023-08-18"
	},
	{
		"id": 60,
		"author": "Ульяна Э.",
		"rating": 5,
		"car": "BMW X4",
		"text": "Стильный SAC! Выделяется из потока. Управляемость отличная.",
		"date": "2023-08-15"
	},
	{
		"id": 61,
		"author": "Руслан Ю.",
		"rating": 5,
		"car": "BMW M4",
		"text": "Легенда среди купе! Каждый выезд - это событие.",
		"date": "2023-08-12"
	},
	{
		"id": 62,
		"author": "Агата Я.",
		"rating": 4,
		"car": "BMW X2",
		"text": "Компактный городской кроссовер. Стильный и практичный.",
		"date": "2023-08-10"
	},
	{
		"id": 63,
		"author": "Илья А.",
		"rating": 5,
		"car": "BMW 5 серии",
		"text": "Бизнес-седан номер один! Комфорт и статус в одном автомобиле.",
		"date": "2023-08-08"
	},
	{
		"id": 64,
		"author": "Диана Б.",
		"rating": 5,
		"car": "BMW i7",
		"text": "Электрический флагман - вау-эффект гарантирован при каждой поездке!",
		"date": "2023-08-05"
	},
	{
		"id": 65,
		"author": "Семён В.",
		"rating": 4,
		"car": "BMW X5",
		"text": "Классический внедорожник BMW. Комфорт и проходимость на высоте.",
		"date": "2023-08-03"
	},
	{
		"id": 66,
		"author": "Милана Г.",
		"rating": 5,
		"car": "BMW 4 серии Кабриолет",
		"text": "Кабриолет мечты! Летом - незабываемые поездки.",
		"date": "2023-08-01"
	},
	{
		"id": 67,
		"author": "Виталий Д.",
		"rating": 5,
		"car": "BMW M5",
		"text": "Суперседан! 625 коней под капотом - это нечто невероятное.",
		"date": "2023-07-28"
	},
	{
		"id": 68,
		"author": "Камила Е.",
		"rating": 4,
		"car": "BMW 3 серии",
		"text": "Классическая трёшка. Надёжная, управляемая, красивая.",
		"date": "2023-07-25"
	},
	{
		"id": 69,
		"author": "Артур Ж.",
		"rating": 5,
		"car": "BMW X7",
		"text": "Большой семейный SAV. Места для всей семьи с запасом!",
		"date": "2023-07-22"
	},
	{
		"id": 70,
		"author": "Элина З.",
		"rating": 5,
		"car": "BMW iX",
		"text": "Электрический внедорожник будущего! Интерьер - произведение искусства.",
		"date": "2023-07-20"
	},
	{
		"id": 71,
		"author": "Даниил И.",
		"rating": 4,
		"car": "BMW X3",
		"text": "Универсальный кроссовер для города и путешествий.",
		"date": "2023-07-18"
	},
	{
		"id": 72,
		"author": "Алиса К.",
		"rating": 5,
		"car": "BMW 7 серии",
		"text": "Роскошь в каждой детали. Машина для тех, кто ценит себя.",
		"date": "2023-07-15"
	},
	{
		"id": 73,
		"author": "Матвей Л.",
		"rating": 5,
		"car": "BMW M3",
		"text": "Икона спортивного седана! Управляемость на высшем уровне.",
		"date": "2023-07-12"
	},
	{
		"id": 74,
		"author": "Аделина М.",
		"rating": 4,
		"car": "BMW X1",
		"text": "Компактный и практичный. Идеален для городских условий.",
		"date": "2023-07-10"
	},
	{
		"id": 75,
		"author": "Захар Н.",
		"rating": 5,
		"car": "BMW 8 серии",
		"text": "Grand Tourer мечты! Дальние поездки стали удовольствием.",
		"date": "2023-07-08"
	},
	{
		"id": 76,
		"author": "Вероника О.",
		"rating": 5,
		"car": "BMW i4",
		"text": "Электрическое Gran Coupé - будущее автомобилестроения!",
		"date": "2023-07-05"
	},
	{
		"id": 77,
		"author": "Тимофей П.",
		"rating": 4,
		"car": "BMW X6",
		"text": "Уникальный SAC. Стиль и мощность в одном.",
		"date": "2023-07-03"
	},
	{
		"id": 78,
		"author": "Есения Р.",
		"rating": 5,
		"car": "BMW 5 серии Touring",
		"text": "Бизнес-универсал высшего класса. Комфорт и практичность.",
		"date": "2023-07-01"
	},
	{
		"id": 79,
		"author": "Богдан С.",
		"rating": 5,
		"car": "BMW X5 M",
		"text": "Спортивный внедорожник - невероятная комбинация!",
		"date": "2023-06-28"
	},
	{
		"id": 80,
		"author": "Анжела Т.",
		"rating": 4,
		"car": "BMW 4 серии",
		"text": "Стильное купе с характером. Дизайн радует каждый день.",
		"date": "2023-06-25"
	},
	{
		"id": 81,
		"author": "Георгий У.",
		"rating": 5,
		"car": "BMW Z4",
		"text": "Классический родстер! Лето стало намного ярче.",
		"date": "2023-06-22"
	},
	{
		"id": 82,
		"author": "Карина Ф.",
		"rating": 5,
		"car": "BMW X3 M",
		"text": "Компактный, но очень мощный SAV. 510 л.с. - это сила!",
		"date": "2023-06-20"
	},
	{
		"id": 83,
		"author": "Ян Х.",
		"rating": 4,
		"car": "BMW 330e",
		"text": "Гибрид для тех, кто хочет экономить без компромиссов.",
		"date": "2023-06-18"
	},
	{
		"id": 84,
		"author": "Стефания Ц.",
		"rating": 5,
		"car": "BMW 2 серии",
		"text": "Маленький спорткар для города. Парковка - легко!",
		"date": "2023-06-15"
	},
	{
		"id": 85,
		"author": "Владислав Ч.",
		"rating": 5,
		"car": "BMW M8",
		"text": "Вершина линейки M! Невероятная машина во всех смыслах.",
		"date": "2023-06-12"
	},
	{
		"id": 86,
		"author": "Эмилия Ш.",
		"rating": 4,
		"car": "BMW iX1",
		"text": "Электрический X1 - практичный выбор для города.",
		"date": "2023-06-10"
	},
	{
		"id": 87,
		"author": "Марк Щ.",
		"rating": 5,
		"car": "BMW 320i",
		"text": "Базовая трёшка - уже отличный автомобиль! BMW есть BMW.",
		"date": "2023-06-08"
	},
	{
		"id": 88,
		"author": "Виолетта Э.",
		"rating": 5,
		"car": "BMW X7",
		"text": "Семейный флагман! Комфорт для всех семи пассажиров.",
		"date": "2023-06-05"
	},
	{
		"id": 89,
		"author": "Давид Ю.",
		"rating": 4,
		"car": "BMW X4",
		"text": "SAC с характером. Выделяется дизайном и ходовыми качествами.",
		"date": "2023-06-03"
	},
	{
		"id": 90,
		"author": "Амина Я.",
		"rating": 5,
		"car": "BMW 7 серии",
		"text": "Новая семёрка - это технологии будущего сегодня!",
		"date": "2023-06-01"
	},
	{
		"id": 91,
		"author": "Кирилл А.",
		"rating": 5,
		"car": "BMW X5",
		"text": "Идеальный баланс комфорта и спортивности в классе SUV.",
		"date": "2023-05-28"
	},
	{
		"id": 92,
		"author": "Полина Б.",
		"rating": 4,
		"car": "BMW 5 серии",
		"text": "Бизнес-седан с отличной управляемостью. Для города и трассы.",
		"date": "2023-05-25"
	},
	{
		"id": 93,
		"author": "Роберт В.",
		"rating": 5,
		"car": "BMW iX",
		"text": "Лучший электрический SUV на рынке! Дизайн, технологии, комфорт.",
		"date": "2023-05-22"
	},
	{
		"id": 94,
		"author": "Арина Г.",
		"rating": 5,
		"car": "BMW M4",
		"text": "Спортивное купе мечты! Каждая поездка - адреналин.",
		"date": "2023-05-20"
	},
	{
		"id": 95,
		"author": "Платон Д.",
		"rating": 4,
		"car": "BMW X3",
		"text": "Надёжный средний кроссовер. Хороший выбор для семьи.",
		"date": "2023-05-18"
	},
	{
		"id": 96,
		"author": "Ангелина Е.",
		"rating": 5,
		"car": "BMW 3 серии",
		"text": "Классика BMW! Управляемость эталонная для своего класса.",
		"date": "2023-05-15"
	},
	{
		"id": 97,
		"author": "Тихон Ж.",
		"rating": 5,
		"car": "BMW 8 серии",
		"text": "GT-автомобиль высшего класса. Путешествия стали удовольствием.",
		"date": "2023-05-12"
	},
	{
		"id": 98,
		"author": "Злата З.",
		"rating": 4,
		"car": "BMW X2",
		"text": "Молодёжный кроссовер. Стильный и динамичный.",
		"date": "2023-05-10"
	},
	{
		"id": 99,
		"author": "Лев И.",
		"rating": 5,
		"car": "BMW M5",
		"text": "Суперседан для тех, кто может себе это позволить. Невероятен!",
		"date": "2023-05-08"
	},
	{
		"id": 100,
		"author": "Маргарита К.",
		"rating": 5,
		"car": "BMW i7",
		"text": "Электрическая роскошь! Theatre Screen - это надо испытать лично.",
		"date": "2023-05-05"
	}
]
